quicklook/__init__.py
quicklook/example_arrays.py
quicklook/quicklook.py
quicklook-1.1.0.dist-info/entry_points.txt
quicklook-1.1.0.dist-info/LICENSE
quicklook-1.1.0.dist-info/WHEEL
quicklook-1.1.0.dist-info/METADATA
quicklook-1.1.0.dist-info/RECORD
