Metadata-Version: 2.1
Name: quicklook
Version: 1.1.0
Summary: An easy way to view numpy arrays
Home-page: https://samsammurphy.github.io/quicklook/
License: BSD-2-Clause
Author: Sam Murphy
Author-email: samsammurphy@gmail.com
Requires-Python: >=3.8,<4.0
Classifier: Development Status :: 3 - Alpha
Classifier: Framework :: Matplotlib
Classifier: Framework :: Pytest
Classifier: License :: OSI Approved :: BSD License
Classifier: Programming Language :: Python
Classifier: Programming Language :: Python :: 3
Classifier: Programming Language :: Python :: 3.8
Classifier: Programming Language :: Python :: 3.9
Classifier: Programming Language :: Python :: 3.10
Classifier: Programming Language :: Python :: 3.11
Classifier: Topic :: Multimedia :: Graphics
Classifier: Topic :: Scientific/Engineering :: Image Processing
Classifier: Topic :: Scientific/Engineering :: Visualization
Classifier: Topic :: Software Development :: Libraries :: Python Modules
Requires-Dist: matplotlib (>=3.6.2,<4.0.0)
Requires-Dist: numpy (>=1.23.4,<2.0.0)
Requires-Dist: rich (>=12.6.0,<13.0.0)
Requires-Dist: typer (>=0.7.0,<0.8.0)
Project-URL: Repository, https://github.com/samsammurphy/quicklook
